pyriksdagen/__init__.py
pyriksdagen/args.py
pyriksdagen/data/queries/alias.rq
pyriksdagen/data/queries/explicit_no_party.rq
pyriksdagen/data/queries/external_identifiers.rq
pyriksdagen/data/queries/government.rq
pyriksdagen/data/queries/member_of_parliament.rq
pyriksdagen/data/queries/member_of_parliament.txt
pyriksdagen/data/queries/minister.rq
pyriksdagen/data/queries/minister.txt
pyriksdagen/data/queries/name_location_specifier.rq
pyriksdagen/data/queries/party_affiliation.rq
pyriksdagen/data/queries/person.rq
pyriksdagen/data/queries/place_of_birth.rq
pyriksdagen/data/queries/place_of_death.rq
pyriksdagen/data/queries/portraits.rq
pyriksdagen/data/queries/speaker.rq
pyriksdagen/data/queries/speaker.txt
pyriksdagen/data/queries/twitter.rq
pyriksdagen/data/queries/wiki_id.rq
pyriksdagen/data/queries_backup/alias.rq
pyriksdagen/data/queries_backup/government.rq
pyriksdagen/data/queries_backup/member_of_parliament.rq
pyriksdagen/data/queries_backup/minister.rq
pyriksdagen/data/queries_backup/name_location_specifier.rq
pyriksdagen/data/queries_backup/party_affiliation.rq
pyriksdagen/data/queries_backup/person.rq
pyriksdagen/data/queries_backup/speaker.rq
pyriksdagen/data/queries_backup/twitter.rq
pyriksdagen/data/segmentation/detection.csv
pyriksdagen/data/segmentation/patterns.json
pyriksdagen/dataset.py
pyriksdagen/date_handling.py
pyriksdagen/db.py
pyriksdagen/download.py
pyriksdagen/export.py
pyriksdagen/io.py
pyriksdagen/match_mp.py
pyriksdagen/metadata.py
pyriksdagen/motions/__init__.py
pyriksdagen/motions/curate.py
pyriksdagen/mp.py
pyriksdagen/reference_handling.py
pyriksdagen/refine.py
pyriksdagen/requirements.txt
pyriksdagen/segmentation.py
pyriksdagen/swerik_catalog.py
pyriksdagen/utils.py
pyriksdagen/wikidata.py
pyriksdagen-1.10.0.dist-info/LICENSE
pyriksdagen-1.10.0.dist-info/METADATA
pyriksdagen-1.10.0.dist-info/WHEEL
pyriksdagen-1.10.0.dist-info/RECORD
